[
        { "child": "David Pettit", "parent": "Jim Pettit" },
        { "child": "Jim Pettit", "parent": "" },
        { "child": "James Pettit", "parent": "David Pettit" },
        { "child": "Mike Pettit", "parent": "David Pettit" },
        { "child": "Anna McCabe", "parent": "David Pettit" },
        { "child": "Hailey Ferreira", "parent": "Anna McCabe" },
        { "child": "Emma McCabe", "parent": "Anna McCabe" },
        { "child": "Kaiden Pettit", "parent": "James Pettit" },
        { "child": "Connor Pettit", "parent": "Mike Pettit" },
        { "child": "Victoria Pettit", "parent": "Mike Pettit" },
        { "child": "Jiminy Cricket", "parent": "Victoria Pettit" },
        { "child": "Toad Stool", "parent": "Jiminy Cricket" },
        { "child": "Super Man", "parent": "Jiminy Cricket" }
      ]